size_constrained_clustering/__init__.py
size_constrained_clustering/base.py
size_constrained_clustering/da.py
size_constrained_clustering/equal.py
size_constrained_clustering/fcm.py
size_constrained_clustering/minmax.py
size_constrained_clustering/shrinkage.py
size_constrained_clustering/k_means_constrained/__init__.py
size_constrained_clustering/k_means_constrained/k_means_constrained_.py
size_constrained_clustering/k_means_constrained/mincostflow_vectorized.py
size_constrained_clustering/k_means_constrained/mincostflow_vectorized_.cpython-36m-darwin.so
size_constrained_clustering/sklearn_import/__init__.py
size_constrained_clustering/sklearn_import/base.py
size_constrained_clustering/sklearn_import/exceptions.py
size_constrained_clustering/sklearn_import/fixes.py
size_constrained_clustering/sklearn_import/funcsigs.py
size_constrained_clustering/sklearn_import/cluster/__init__.py
size_constrained_clustering/sklearn_import/cluster/_k_means.cpython-36m-darwin.so
size_constrained_clustering/sklearn_import/cluster/k_means_.py
size_constrained_clustering/sklearn_import/externals/__init__.py
size_constrained_clustering/sklearn_import/externals/funcsigs.py
size_constrained_clustering/sklearn_import/metrics/__init__.py
size_constrained_clustering/sklearn_import/metrics/pairwise.py
size_constrained_clustering/sklearn_import/metrics/pairwise_fast.cpython-36m-darwin.so
size_constrained_clustering/sklearn_import/preprocessing/__init__.py
size_constrained_clustering/sklearn_import/preprocessing/data.py
size_constrained_clustering/sklearn_import/utils/__init__.py
size_constrained_clustering/sklearn_import/utils/extmath.py
size_constrained_clustering/sklearn_import/utils/fixes.py
size_constrained_clustering/sklearn_import/utils/sparsefuncs.py
size_constrained_clustering/sklearn_import/utils/sparsefuncs_fast.cpython-36m-darwin.so
size_constrained_clustering/sklearn_import/utils/validation.py
size_constrained_clustering-0.1.2.dist-info/LICENSE
size_constrained_clustering-0.1.2.dist-info/METADATA
size_constrained_clustering-0.1.2.dist-info/WHEEL
size_constrained_clustering-0.1.2.dist-info/top_level.txt
size_constrained_clustering-0.1.2.dist-info/RECORD
