Metadata-Version: 2.1
Name: size-constrained-clustering
Version: 0.1.2
Summary: Size Constrained Clustering solver
Home-page: https://github.com/jingw2/size_constrained_clustering
Author: Jing Wang
Author-email: jingw2@foxmail.com
License: MIT
Platform: UNKNOWN
Requires-Python: ==3.6
Requires-Dist: joblib (==0.15.1)
Requires-Dist: psutil (>=5.6.6)
Requires-Dist: numpy (>=1.13.0)
Requires-Dist: scipy (==1.4.1)
Requires-Dist: ortools (>=6.7)
Requires-Dist: six (==1.12.0)
Requires-Dist: matplotlib (==3.1.0)
Requires-Dist: seaborn (==0.10.1)
Requires-Dist: Cython (==0.29.20)
Requires-Dist: scikit-learn (==0.23.1)
